spiegeltools/cleaning/__init__.py
spiegeltools/cleaning/ukdata_cleaning.py
spiegeltools/graphs/__init__.py
spiegeltools/htmlgen/__init__.py
spiegeltools/maps/__init__.py
spiegeltools-0.1.4.dist-info/METADATA
spiegeltools-0.1.4.dist-info/WHEEL
spiegeltools-0.1.4.dist-info/top_level.txt
spiegeltools-0.1.4.dist-info/RECORD
