Metadata-Version: 2.4
Name: spiegeltools
Version: 0.1.4
Summary: Provides data analysis tool for government crime data.
Author-email: Igor Carvalheira <igorccarvalheira111@gmail.com>
Requires-Python: >=3.8
Requires-Dist: requests>=2.25.1
Requires-Dist: polars>=1.31.0
Requires-Dist: geopandas>=1.1.1
